[{"id":0,"parent":11,"joint":"hinge","name":"lever","parts":[{"id":48,"name":"lever","children":[]}],"jointData":{"axis":{"origin":[-0.06789344420656562,0.07856660777135693,0],"direction":[0,0,1]},"limit":{"a":0,"b":18.36,"noLimit":false}}},{"id":1,"parent":13,"joint":"hinge","name":"wheel","parts":[{"id":41,"name":"wheel","children":[]}],"jointData":{"axis":{"origin":[0.0992845498061307,-0.7724105,-0.03254063003487493],"direction":[-0.3114497151998492,0,-0.9502626346973415]},"limit":{"a":0,"b":0,"noLimit":true}}},{"id":2,"parent":13,"joint":"hinge","name":"wheel","parts":[{"id":42,"name":"wheel","children":[]}],"jointData":{"axis":{"origin":[0.0992845498061307,-0.7724105,-0.03254063003487493],"direction":[-0.3114497151998492,0,-0.9502626346973415]},"limit":{"a":0,"b":0,"noLimit":true}}},{"id":3,"parent":14,"joint":"hinge","name":"wheel","parts":[{"id":37,"name":"wheel","children":[]}],"jointData":{"axis":{"origin":[0.11366920558191895,-0.7724105,0.15563188487680593],"direction":[0.8075438209519561,0,-0.5898075764538084]},"limit":{"a":0,"b":0,"noLimit":true}}},{"id":4,"parent":14,"joint":"hinge","name":"wheel","parts":[{"id":38,"name":"wheel","children":[]}],"jointData":{"axis":{"origin":[0.11366920558191895,-0.7724105,0.15563188487680593],"direction":[0.8075438209519561,0,-0.5898075764538084]},"limit":{"a":0,"b":0,"noLimit":true}}},{"id":5,"parent":15,"joint":"hinge","name":"wheel","parts":[{"id":33,"name":"wheel","children":[]}],"jointData":{"axis":{"origin":[-0.10893206364454598,-0.7724105,0.15074318419851823],"direction":[0.8105210053801724,0,0.5857095695287168]},"limit":{"a":0,"b":0,"noLimit":true}}},{"id":6,"parent":15,"joint":"hinge","name":"wheel","parts":[{"id":34,"name":"wheel","children":[]}],"jointData":{"axis":{"origin":[-0.10893206364454598,-0.7724105,0.15074318419851823],"direction":[0.8105210053801724,0,0.5857095695287168]},"limit":{"a":0,"b":0,"noLimit":true}}},{"id":7,"parent":16,"joint":"hinge","name":"wheel","parts":[{"id":29,"name":"wheel","children":[]}],"jointData":{"axis":{"origin":[-0.0890578648291246,-0.7724105,-0.028685456959102604],"direction":[-0.306587611084101,0,0.9518424432277353]},"limit":{"a":0,"b":0,"noLimit":true}}},{"id":8,"parent":16,"joint":"hinge","name":"wheel","parts":[{"id":30,"name":"wheel","children":[]}],"jointData":{"axis":{"origin":[-0.0890578648291246,-0.7724105,-0.028685456959102604],"direction":[-0.306587611084101,0,0.9518424432277353]},"limit":{"a":0,"b":0,"noLimit":true}}},{"id":9,"parent":17,"joint":"hinge","name":"wheel","parts":[{"id":23,"name":"wheel","children":[]}],"jointData":{"axis":{"origin":[-0.00010778227419602529,-0.7724105,-0.04312558927971338],"direction":[-0.9999968768520557,0,0.002499257116506058]},"limit":{"a":0,"b":0,"noLimit":true}}},{"id":10,"parent":17,"joint":"hinge","name":"wheel","parts":[{"id":24,"name":"wheel","children":[]}],"jointData":{"axis":{"origin":[-0.00010778227419602529,-0.7724105,-0.04312558927971338],"direction":[-0.9999968768520557,0,0.002499257116506058]},"limit":{"a":0,"b":0,"noLimit":true}}},{"id":11,"parent":12,"joint":"slider","name":"seat_soft_surface","parts":[{"id":59,"name":"seat_soft_surface","children":[]},{"id":75,"name":"back_soft_surface","children":[]},{"id":74,"name":"back_connector","children":[]},{"id":76,"name":"back_support","children":[]},{"id":67,"name":"armrest_soft_surface","children":[]},{"id":68,"name":"arm_vertical_bar","children":[]},{"id":69,"name":"arm_horizontal_bar","children":[]},{"id":70,"name":"arm_connector","children":[]},{"id":83,"name":"other_leaf","children":[]},{"id":61,"name":"arm_vertical_bar","children":[]},{"id":62,"name":"arm_horizontal_bar","children":[]},{"id":63,"name":"arm_connector","children":[]},{"id":64,"name":"armrest_soft_surface","children":[]},{"id":85,"name":"other_leaf","children":[]},{"id":45,"name":"central_support","children":[]},{"id":47,"name":"seat_connector","children":[]},{"id":52,"name":"seat_connector","children":[]},{"id":49,"name":"mounting_plate","children":[]}],"jointData":{"axis":{"origin":[0.002711,0,0.07935049999999999],"direction":[0,-1,0]},"limit":{"a":0,"b":0.1120000000000001,"noLimit":false,"rotates":true,"noRotationLimit":true,"rotationLimit":0}}},{"id":12,"parent":-1,"joint":"free","name":"central_support","parts":[{"id":43,"name":"central_support","children":[]},{"id":44,"name":"central_support","children":[]},{"id":50,"name":"central_support","children":[]},{"id":12,"name":"leg","children":[]},{"id":13,"name":"leg","children":[]},{"id":14,"name":"leg","children":[]},{"id":15,"name":"leg","children":[]},{"id":16,"name":"leg","children":[]},{"id":53,"name":"footrest_bar","children":[]},{"id":54,"name":"footrest_bar","children":[]},{"id":55,"name":"footrest_bar","children":[]},{"id":56,"name":"footrest_bar","children":[]},{"id":57,"name":"footrest_circular","children":[]},{"id":78,"name":"other_leaf","children":[]},{"id":79,"name":"other_leaf","children":[]},{"id":80,"name":"other_leaf","children":[]},{"id":81,"name":"other_leaf","children":[]}],"jointData":{}},{"id":13,"parent":12,"joint":"hinge","name":"caster_yoke","parts":[{"id":39,"name":"caster_yoke","children":[]},{"id":40,"name":"caster_stem","children":[]}],"jointData":{"axis":{"origin":[0.29709290116600373,0,0.48178319398055136],"direction":[0,1,0]},"limit":{"a":0,"b":0,"noLimit":true}}},{"id":14,"parent":12,"joint":"hinge","name":"caster_yoke","parts":[{"id":35,"name":"caster_yoke","children":[]},{"id":36,"name":"caster_stem","children":[]}],"jointData":{"axis":{"origin":[-0.28564962011056766,0,0.4816866997176729],"direction":[0,1,0]},"limit":{"a":0,"b":0,"noLimit":true}}},{"id":15,"parent":12,"joint":"hinge","name":"caster_yoke","parts":[{"id":31,"name":"caster_yoke","children":[]},{"id":32,"name":"caster_stem","children":[]}],"jointData":{"axis":{"origin":[-0.4654745015104084,0,-0.07262785970930954],"direction":[0,1,0]},"limit":{"a":0,"b":0,"noLimit":true}}},{"id":16,"parent":12,"joint":"hinge","name":"caster_yoke","parts":[{"id":27,"name":"caster_yoke","children":[]},{"id":28,"name":"caster_stem","children":[]}],"jointData":{"axis":{"origin":[0.006070740697148607,0,-0.41522137157966515],"direction":[0,1,0]},"limit":{"a":0,"b":0,"noLimit":true}}},{"id":17,"parent":12,"joint":"hinge","name":"caster_yoke","parts":[{"id":25,"name":"caster_yoke","children":[]},{"id":26,"name":"caster_stem","children":[]}],"jointData":{"axis":{"origin":[0.47751959842131086,0,-0.07210110052099139],"direction":[0,1,0]},"limit":{"a":0,"b":0,"noLimit":true}}}]