[{"objs": ["new-3", "new-2", "new-1", "original-2"], "name": "refrigerator", "id": 0, "text": "refrigerator", "children": [{"objs": ["new-3", "new-2", "new-1", "original-2"], "name": "body", "id": 1, "text": "body", "children": [{"text": "frame", "objs": ["new-3", "new-2"], "name": "frame", "ori_id": 15, "id": 2}, {"objs": ["new-1", "original-2"], "name": "door", "id": 3, "text": "door", "children": [{"text": "door_frame", "objs": ["new-1"], "name": "door_frame", "ori_id": 17, "id": 4}, {"text": "handle", "objs": ["original-2"], "name": "handle", "ori_id": 18, "id": 5}], "ori_id": 16}], "ori_id": 14}], "ori_id": 0}]